kak_plugins/__init__.py
kak_plugins/apis/__init__.py
kak_plugins/apis/clipboard.py
kak_plugins/apis/git.py
kak_plugins/apis/kak.py
kak_plugins/github_permalink.py
kak_plugins/utils/__init__.py
kak_plugins/utils/line_range.py
kak_plugins/utils/os.py
kak_plugins-0.5.1.dist-info/entry_points.txt
kak_plugins-0.5.1.dist-info/WHEEL
kak_plugins-0.5.1.dist-info/METADATA
kak_plugins-0.5.1.dist-info/RECORD
