Metadata-Version: 2.1
Name: kak-plugins
Version: 0.5.1
Summary: 
Home-page: https://github.com/abstractlyZach/kak_plugins
License: MIT
Keywords: kakoune,plugin
Author: abstractlyZach
Author-email: zach3lee@gmail.com
Requires-Python: >=3.9,<4.0
Classifier: License :: OSI Approved :: MIT License
Classifier: Programming Language :: Python :: 3
Classifier: Programming Language :: Python :: 3.9
Requires-Dist: GitPython (>=3.1.14,<4.0.0)
Requires-Dist: click (>=7.1.2,<8.0.0)
Project-URL: Repository, https://github.com/abstractlyZach/kak_plugins
